MANIFEST.in
README.rst
requirements.txt
setup.py
dl_helper/__init__.py
dl_helper/console_capture.py
dl_helper.egg-info/PKG-INFO
dl_helper.egg-info/SOURCES.txt
dl_helper.egg-info/dependency_links.txt
dl_helper.egg-info/requires.txt
dl_helper.egg-info/top_level.txt
dl_helper/krs/__init__.py
dl_helper/krs/krs_model_io.py
dl_helper/krs/krs_utils.py