Metadata-Version: 1.2
Name: dl-helper
Version: 1.0.0
Summary: Miscellaneous tiny utils to help working with ML/DL tasks in an IPython Notebook context
Home-page: https://github.com/paulovn/dl-helper
Author: Paulo Villegas
Author-email: paulo.vllgs@gmail.com
License: UNKNOWN
Platform: any
Classifier: Development Status :: 4 - Beta
Classifier: Intended Audience :: Developers
Classifier: Programming Language :: Python
Classifier: Programming Language :: Python :: 3
Classifier: License :: OSI Approved :: BSD License
Classifier: Operating System :: OS Independent
Requires-Python: >=3.5
